workpls/__init__.py
workpls/__main__.py
workpls-0.0.6.dist-info/METADATA
workpls-0.0.6.dist-info/WHEEL
workpls-0.0.6.dist-info/entry_points.txt
workpls-0.0.6.dist-info/top_level.txt
workpls-0.0.6.dist-info/RECORD
