Metadata-Version: 2.4
Name: workpls
Version: 0.0.6
Summary: THIS IS RIDICULAS WHY ISNT IT WORKING FOR GOD SAKENS
